ADgui/AD20_GUI_Multiout.py
ADgui/ADgraph_GUI.py
ADgui/ADmath_rev.py
ADgui/ADnum_rev_timed_vis.py
ADgui/__init__.py
ADgui_lindseysbrown-0.0.1.dist-info/LICENSE
ADgui_lindseysbrown-0.0.1.dist-info/METADATA
ADgui_lindseysbrown-0.0.1.dist-info/WHEEL
ADgui_lindseysbrown-0.0.1.dist-info/top_level.txt
ADgui_lindseysbrown-0.0.1.dist-info/RECORD
